{
  "Site": {
    "AutoPrint": "false",
    "PaperOrientation": "0",
    "ReportLayout": "0",
    "CopiesToPrint": "1",
    "InclurePHI": "false",
    "EnableRating": "false"
  },
  "Recorder": {
    "AutoPrint": "false",
    "Printer": "0",
    "PaperOrientation": "0",
    "ReportLayout": "0",
    "CopiesToPrint": "1",
    "InclurePHI": "false",
    "EnableRating": "false"
  },
  "Physician": {
    "AutoPrint": "false",
    "PaperOrientation": "0",
    "ReportLayout": "0",
    "CopiesToPrint": "1",
    "InclurePHI": "false",
    "EnableRating": "false"
  }
}